pokerware/__init__.py
pokerware/cli.py
pokerware/generate.py
pokerware/pokerware-formal.txt
pokerware/pokerware-slang.txt
pokerware-0.1.3.dist-info/LICENSE
pokerware-0.1.3.dist-info/METADATA
pokerware-0.1.3.dist-info/WHEEL
pokerware-0.1.3.dist-info/entry_points.txt
pokerware-0.1.3.dist-info/top_level.txt
pokerware-0.1.3.dist-info/RECORD
