Metadata-Version: 2.1
Name: pokerware
Version: 0.1.3
Summary: Generate passwords via playing cards
Home-page: http://github.com/buckley-w-david/Pokerware
Author: David Buckley
Author-email: buckley.w.david@gmail.com
License: MIT
Platform: UNKNOWN
Classifier: Development Status :: 3 - Alpha
Classifier: License :: OSI Approved :: MIT License
Classifier: Programming Language :: Python :: 3.6
